gamecreator_auth_database/__init__.py
gamecreator_auth_database/auth_secret_key.py
gamecreator_auth_database/gamecreator_auth.py
gamecreator_auth_database-1.0.2.dist-info/METADATA
gamecreator_auth_database-1.0.2.dist-info/WHEEL
gamecreator_auth_database-1.0.2.dist-info/RECORD
